nominatim_db/__init__.py
nominatim_db/cli.py
nominatim_db/config.py
nominatim_db/errors.py
nominatim_db/typing.py
nominatim_db/version.py
nominatim_db/clicmd/__init__.py
nominatim_db/clicmd/add_data.py
nominatim_db/clicmd/admin.py
nominatim_db/clicmd/api.py
nominatim_db/clicmd/args.py
nominatim_db/clicmd/convert.py
nominatim_db/clicmd/export.py
nominatim_db/clicmd/freeze.py
nominatim_db/clicmd/index.py
nominatim_db/clicmd/refresh.py
nominatim_db/clicmd/replication.py
nominatim_db/clicmd/setup.py
nominatim_db/clicmd/special_phrases.py
nominatim_db/data/__init__.py
nominatim_db/data/country_info.py
nominatim_db/data/place_info.py
nominatim_db/data/place_name.py
nominatim_db/data/postcode_format.py
nominatim_db/db/__init__.py
nominatim_db/db/connection.py
nominatim_db/db/properties.py
nominatim_db/db/query_pool.py
nominatim_db/db/sql_preprocessor.py
nominatim_db/db/status.py
nominatim_db/db/utils.py
nominatim_db/indexer/__init__.py
nominatim_db/indexer/indexer.py
nominatim_db/indexer/progress.py
nominatim_db/indexer/runners.py
nominatim_db/tokenizer/__init__.py
nominatim_db/tokenizer/base.py
nominatim_db/tokenizer/factory.py
nominatim_db/tokenizer/icu_rule_loader.py
nominatim_db/tokenizer/icu_token_analysis.py
nominatim_db/tokenizer/icu_tokenizer.py
nominatim_db/tokenizer/place_sanitizer.py
nominatim_db/tokenizer/sanitizers/__init__.py
nominatim_db/tokenizer/sanitizers/base.py
nominatim_db/tokenizer/sanitizers/clean_housenumbers.py
nominatim_db/tokenizer/sanitizers/clean_postcodes.py
nominatim_db/tokenizer/sanitizers/clean_tiger_tags.py
nominatim_db/tokenizer/sanitizers/config.py
nominatim_db/tokenizer/sanitizers/delete_tags.py
nominatim_db/tokenizer/sanitizers/split_name_list.py
nominatim_db/tokenizer/sanitizers/strip_brace_terms.py
nominatim_db/tokenizer/sanitizers/tag_analyzer_by_language.py
nominatim_db/tokenizer/sanitizers/tag_japanese.py
nominatim_db/tokenizer/token_analysis/__init__.py
nominatim_db/tokenizer/token_analysis/base.py
nominatim_db-5.1.0.dist-info/METADATA
nominatim_db-5.1.0.dist-info/WHEEL
nominatim_db-5.1.0.dist-info/RECORD
